{
  "alfredtheme" : {
    "result" : {
      "textSpacing" : 6,
      "subtext" : {
        "size" : 11,
        "colorSelected" : "#FEFFFFFF",
        "font" : "Helvetica",
        "color" : "#00000087"
      },
      "shortcut" : {
        "size" : 16,
        "colorSelected" : "#FDFCFF00",
        "font" : "Helvetica",
        "color" : "#FDFCFF00"
      },
      "backgroundSelected" : "#00000035",
      "text" : {
        "size" : 16,
        "colorSelected" : "#FEFFFFFF",
        "font" : "Helvetica",
        "color" : "#00000087"
      },
      "iconPaddingHorizontal" : 5,
      "paddingVertical" : 6,
      "iconSize" : 40
    },
    "search" : {
      "paddingVertical" : 2,
      "background" : "#00000000",
      "spacing" : 10,
      "text" : {
        "size" : 36,
        "colorSelected" : "#000000FF",
        "font" : "Helvetica",
        "color" : "#000000FF"
      },
      "backgroundSelected" : "#D1CC99FF"
    },
    "window" : {
      "color" : "#EAEAEACC",
      "paddingHorizontal" : 10,
      "width" : 560,
      "borderPadding" : 10,
      "borderColor" : "#FEFFFF00",
      "blur" : 0,
      "roundness" : 12,
      "paddingVertical" : 10
    },
    "credit" : "Ddyracer",
    "separator" : {
      "color" : "#CBD8CB00",
      "thickness" : 1
    },
    "scrollbar" : {
      "color" : "#FEFFFF47",
      "thickness" : 2
    },
    "name" : "OS X Dock (v2)"
  }
}